agenterprise/__init__.py
agenterprise/__main__.py
agenterprise/agent_grammer/__init__.py
agenterprise/agent_grammer/examples/__init__.py
agenterprise/agent_grammer/examples/agentmicroservice.py
agenterprise/agent_grammer/parser/__init__.py
agenterprise/agent_grammer/parser/ai_environmentLexer.py
agenterprise/agent_grammer/parser/ai_environmentListener.py
agenterprise/agent_grammer/parser/ai_environmentParser.py
agenterprise/agent_grammer/parser/ai_environmentVisitor.py
agenterprise/agent_grammer/support/llms_txt.py
agenterprise/model/__init__.py
agenterprise/model/project.py
agenterprise/model/data/__init__.py
agenterprise/model/data/ai_environment.py
agenterprise/model/listener/AIURN.py
agenterprise/model/listener/__init__.py
agenterprise/model/listener/agent/__init__.py
agenterprise/model/listener/agent/listener.py
agenterprise/model/listener/agenticmiddleware/listener.py
agenterprise/model/listener/entity/__init__.py
agenterprise/model/listener/entity/listener.py
agenterprise/model/listener/llm/__init__.py
agenterprise/model/listener/llm/listener.py
agenterprise/model/listener/nonfunctional/__init__.py
agenterprise/model/listener/nonfunctional/listener.py
agenterprise/model/listener/service/__init__.py
agenterprise/model/listener/service/listener.py
agenterprise/model/listener/tool/__init__.py
agenterprise/model/listener/tool/listener.py
agenterprise-0.1.14.dist-info/licenses/LICENSE
agenterprise-0.1.14.dist-info/METADATA
agenterprise-0.1.14.dist-info/WHEEL
agenterprise-0.1.14.dist-info/entry_points.txt
agenterprise-0.1.14.dist-info/top_level.txt
agenterprise-0.1.14.dist-info/RECORD
