Metadata-Version: 2.4
Name: agenterprise
Version: 0.1.14
Summary: Generator for AI Environments
Author-email: Michael Vonrueden <mail@agenterprise.ai>
License-Expression: MIT
Project-URL: Homepage, https://agenterprise.ai
Project-URL: Repository, https://github.com/agenterprise/agenterprise
Keywords: AI,agent,mdsd,enterprise,codegen
Classifier: Development Status :: 3 - Alpha
Classifier: Intended Audience :: Developers
Classifier: Programming Language :: Python :: 3
Classifier: Programming Language :: Python :: 3.12
Classifier: Topic :: Software Development :: Code Generators
Classifier: Topic :: Software Development :: Libraries :: Python Modules
Classifier: Operating System :: OS Independent
Requires-Python: >=3.12
License-File: LICENSE
Requires-Dist: antlr4-python3-runtime>=4.13.2
Requires-Dist: antlr4-tools>=0.2.2
Requires-Dist: cookiecutter>=2.6.0
Requires-Dist: jinja2>=3.1.6
Requires-Dist: pydantic>=2.11.7
Requires-Dist: pyproject-parser>=0.13.0
Requires-Dist: setuptools>=80.9.0
Provides-Extra: dev
Requires-Dist: pytest>=8.4.2; extra == "dev"
Requires-Dist: build>=1.3.0; extra == "dev"
Requires-Dist: twine>=6.2.0; extra == "dev"
Dynamic: license-file
